{
  "type": "FeatureCollection",
  "features": [
    {
      "type": "Feature",
      "geometry": {
        "type": "LineString",
        "coordinates": [
          [
            1.4085674285888672,
            42.53588010092859
          ],
          [
            1.4511394500732422,
            42.539927630324506
          ],
          [
            1.4634990692138672,
            42.50146550893478
          ],
          [
            1.4071941375732422,
            42.49336520339777
          ],
          [
            1.4374065399169922,
            42.47108395294282
          ],
          [
            1.4374065399169922,
            42.42852498752538
          ],
          [
            1.5472698211669922,
            42.43055226061956
          ],
          [
            1.5651226043701172,
            42.44980808481614
          ],
          [
            1.6598796844482422,
            42.47108395294282
          ],
          [
            1.6749858856201172,
            42.49842801732158
          ],
          [
            1.7312908172607422,
            42.50146550893478
          ],
          [
            1.7409038543701172,
            42.55813826591759
          ],
          [
            1.7862224578857422,
            42.56825298997905
          ],
          [
            1.7326641082763672,
            42.59151063198148
          ],
          [
            1.7395305633544922,
            42.61779143282346
          ],
          [
            1.5939617156982422,
            42.625875602591364
          ],
          [
            1.5747356414794922,
            42.6531519257789
          ],
          [
            1.4813518524169922,
            42.64810165693524
          ],
          [
            1.4744853973388672,
            42.60869548716233
          ],
          [
            1.4360332489013672,
            42.60060908689335
          ],
          [
            1.4085674285888672,
            42.53588010092859
          ]
        ]
      },
      "properties": {}
    }
  ]
}
